ashcrypt/__init__.py
ashcrypt/__main__.py
ashcrypt/crypt.py
ashcrypt/database.py
ashcrypt/datacrypt.py
ashcrypt/filecrypt.py
ashcrypt/gui.py
ashcrypt/sandbox/__init__.py
ashcrypt/sandbox/clicrypt.py
ashcrypt/tests/__init__.py
ashcrypt/tests/test_crypt.py
ashcrypt/utils/__init__.py
ashcrypt/utils/consts/__init__.py
ashcrypt/utils/consts/main.py
ashcrypt/utils/exceptions/__init__.py
ashcrypt/utils/exceptions/dynamic.py
ashcrypt/utils/exceptions/fixed.py
ashcrypt/utils/safepack/__init__.py
ashcrypt/utils/safepack/file.py
ashcrypt/utils/safepack/qr.py
ashcrypt/utils/safepack/text.py
ashcrypt-4.0.0.dist-info/LICENSE
ashcrypt-4.0.0.dist-info/METADATA
ashcrypt-4.0.0.dist-info/WHEEL
ashcrypt-4.0.0.dist-info/top_level.txt
ashcrypt-4.0.0.dist-info/RECORD
