Metadata-Version: 2.1
Name: ashcrypt
Version: 4.0.0
Summary: The predecessor of litecrypt, where all the testing and trial-and-error took place. NOTE: THIS IS NOT STABLE.
Home-page: https://github.com/AshGw/AES-256.git
Author: Ashref Gwader
Author-email: AshrefGw@proton.me
Keywords: Cryptography application,cryptography libraryAES-256
Classifier: Development Status :: 5 - Production/Stable
Classifier: Intended Audience :: Developers
Classifier: License :: OSI Approved :: MIT License
Classifier: Operating System :: OS Independent
Classifier: Programming Language :: Python
Classifier: Programming Language :: Python :: 3
Classifier: Programming Language :: Python :: 3.7
Classifier: Programming Language :: Python :: 3.8
Classifier: Programming Language :: Python :: 3.9
Classifier: Programming Language :: Python :: 3.10
Classifier: Programming Language :: Python :: 3.11
Requires-Python: >=3.7
License-File: LICENSE
Requires-Dist: bcrypt ==4.0.1
Requires-Dist: cryptography ==40.0.2
Requires-Dist: qrcode ==7.4.2
Requires-Dist: ttkbootstrap ==1.10.1
